spotify_dl/__init__.py
spotify_dl/constants.py
spotify_dl/scaffold.py
spotify_dl/spotify.py
spotify_dl/spotify_dl.py
spotify_dl/utils.py
spotify_dl/youtube.py
spotify_dl-8.9.0.dist-info/LICENSE
spotify_dl-8.9.0.dist-info/METADATA
spotify_dl-8.9.0.dist-info/WHEEL
spotify_dl-8.9.0.dist-info/entry_points.txt
spotify_dl-8.9.0.dist-info/top_level.txt
spotify_dl-8.9.0.dist-info/RECORD
