Metadata-Version: 2.1
Name: spotify_dl
Version: 8.9.0
Summary: Downloads songs from a Spotify Playlist/Track/Album that you provide
Home-page: https://github.com/SathyaBhat/spotify-dl/
Author: Sathya Bhat
Author-email: sathya@sathyasays.com
License: MIT
Classifier: Development Status :: 5 - Production/Stable
Classifier: License :: OSI Approved :: MIT License
Classifier: Operating System :: POSIX
Classifier: Natural Language :: English
Classifier: Operating System :: OS Independent
Classifier: Programming Language :: Python
Classifier: Programming Language :: Python :: 3
Classifier: Programming Language :: Python :: 3.7
Classifier: Programming Language :: Python :: 3.8
Classifier: Programming Language :: Python :: 3.9
Classifier: Programming Language :: Python :: 3.10
Classifier: Topic :: Internet
Classifier: Topic :: Software Development :: Libraries
Classifier: Topic :: Software Development :: Libraries :: Python Modules
Classifier: Topic :: Utilities
Requires-Python: >=3.7
License-File: LICENSE
Requires-Dist: sentry_sdk~=1.16
Requires-Dist: yt-dlp>=2023.3.4
Requires-Dist: spotipy~=2.21
Requires-Dist: mutagen~=1.45
Requires-Dist: rich~=12.0
Requires-Dist: urllib3~=1.26
